Metadata-Version: 1.1
Name: bluread
Version: 1.4
Summary: Python wrapper for libbluray
Home-page: https://github.com/cmlburnett/PyBluRead
Author: Colin ML Burnett
Author-email: cmlburnett@gmail.com
License: UNKNOWN
Download-URL: https://pypi.python.org/pypi/bluread
Platform: UNKNOWN
Classifier: Programming Language :: Python :: 3.4
Classifier: Programming Language :: Python :: 3.5
Requires: crudexml
